<?xml version="1.0" encoding="utf-8" ?><dwsync><file name=".htaccess" server="wwwww.iwantcreative.comw.iwantcreative.com/htdocs/iwantcreative/" local="3576527640" remote="-4611778803317946997" /><file name="admintools.css" server="wwwww.iwantcreative.comw.iwantcreative.com/htdocs/iwantcreative/" local="3581625679" remote="-4611778803317946996" /><file name="component.css" server="wwwww.iwantcreative.comw.iwantcreative.com/htdocs/iwantcreative/" local="3576527520" remote="-4611778803317946992" /><file name="components.css" server="wwwww.iwantcreative.comw.iwantcreative.com/htdocs/iwantcreative/" local="3579635870" remote="-4611778803317946992" /><file name="inspector.css" server="wwwww.iwantcreative.comw.iwantcreative.com/htdocs/iwantcreative/" local="3576527520" remote="-4611778803317946988" /><file name="menu.css" server="wwwww.iwantcreative.comw.iwantcreative.com/htdocs/iwantcreative/" local="3582556480" remote="-4611778803317946987" /><file name="sitelive.css" server="wwwww.iwantcreative.comw.iwantcreative.com/htdocs/iwantcreative/" local="3576527520" remote="-4611778803317946987" /><file name="styles.css" server="wwwww.iwantcreative.comw.iwantcreative.com/htdocs/iwantcreative/" local="3576527520" remote="-4611778803317946987" /><file name="trackeditor.css" server="wwwww.iwantcreative.comw.iwantcreative.com/htdocs/iwantcreative/" local="3576527520" remote="-4611778803317946986" /></dwsync>